[
{"user":"bot_2245","timestamp":1.773971568E9},
{"user":"bot_2245","timestamp":1.773971569E9},
{"user":"bot_2245","timestamp":1.77397157E9},
{"user":"bot_2245","timestamp":1.773971571E9},
{"user":"bot_2245","timestamp":1.773971572E9},
{"user":"bot_2245","timestamp":1.773971573E9},
{"user":"bot_2245","timestamp":1.773971573E9},
{"user":"bot_2245","timestamp":1.773971574E9},
{"user":"bot_2245","timestamp":1.773971575E9},
{"user":"bot_2245","timestamp":1.773971576E9},
{"user":"bot_2245","timestamp":1.773971577E9},
{"user":"bot_2245","timestamp":1.773971578E9},
{"user":"bot_2245","timestamp":1.773971579E9},
{"user":"bot_2245","timestamp":1.77397158E9},
{"user":"bot_2245","timestamp":1.773971581E9},
{"user":"bot_2245","timestamp":1.773971582E9},
{"user":"bot_2245","timestamp":1.773971583E9},
{"user":"bot_2245","timestamp":1.773971583E9},
{"user":"bot_2245","timestamp":1.773971584E9},
{"user":"bot_2245","timestamp":1.773971585E9},
{"user":"bot_2245","timestamp":1.773971586E9},
{"user":"bot_2245","timestamp":1.773971587E9},
{"user":"bot_2245","timestamp":1.773971588E9},
{"user":"bot_2245","timestamp":1.773971589E9},
{"user":"bot_2245","timestamp":1.77397159E9},
{"user":"bot_2245","timestamp":1.773971591E9},
{"user":"bot_2245","timestamp":1.773971592E9},
{"user":"bot_2245","timestamp":1.773971593E9},
{"user":"bot_2245","timestamp":1.773971593E9}
]